pyside6_settings/__init__.py
pyside6_settings/fields.py
pyside6_settings/loaders/__init__.py
pyside6_settings/loaders/base.py
pyside6_settings/loaders/json.py
pyside6_settings/loaders/toml.py
pyside6_settings/loaders/yaml.py
pyside6_settings/settings.py
pyside6_settings/type_parser.py
pyside6_settings/widgets/__init__.py
pyside6_settings/widgets/path.py
pyside6_settings/widgets/tags.py
pyside6_settings-1.0.3.dist-info/METADATA
pyside6_settings-1.0.3.dist-info/WHEEL
pyside6_settings-1.0.3.dist-info/licenses/LICENSE
pyside6_settings-1.0.3.dist-info/RECORD
