Metadata-Version: 2.4
Name: pyside6-settings
Version: 1.0.3
Summary: Automatic UI generation for PySide6 settings from Pydantic models
License: MIT
License-File: LICENSE
Keywords: pyside6,qt,settings,configuration,pydantic,ui,forms,gui
Author: Vladyslav Chaliuk
Author-email: chaliukvladyslav@gmail.com
Requires-Python: >=3.10, <3.14
Classifier: Development Status :: 4 - Beta
Classifier: Intended Audience :: Developers
Classifier: License :: OSI Approved :: MIT License
Classifier: Operating System :: OS Independent
Classifier: Programming Language :: Python :: 3
Classifier: Programming Language :: Python :: 3.10
Classifier: Programming Language :: Python :: 3.11
Classifier: Programming Language :: Python :: 3.12
Classifier: Topic :: Software Development :: Libraries :: Python Modules
Classifier: Topic :: Software Development :: User Interfaces
Classifier: Topic :: Software Development :: Widget Sets
Classifier: Framework :: Pydantic
Classifier: Framework :: Pydantic :: 2
Provides-Extra: all
Provides-Extra: toml
Provides-Extra: yaml
Requires-Dist: pydantic (>=2.12.4,<3.0.0)
Requires-Dist: pyside6 (>=6.10.0,<7.0.0)
Requires-Dist: pyyaml (>=6.0.3,<7.0.0) ; extra == "all"
Requires-Dist: pyyaml (>=6.0.3,<7.0.0) ; extra == "yaml"
Requires-Dist: toml (>=0.10.2,<0.11.0) ; extra == "all"
Requires-Dist: toml (>=0.10.2,<0.11.0) ; extra == "toml"
Project-URL: Homepage, https://github.com/AstralMortem/pyside6-settings
Project-URL: Repository, https://github.com/AstralMortem/pyside6-settings
